coherent/build/__init__.py
coherent/build/__main__.py
coherent/build/backend.py
coherent/build/bootstrap.py
coherent/build/discovery.py
coherent/build/flit.py
coherent/build/layouts.py
coherent/build/metadata.py
coherent/build/system.toml
coherent/build/compat/py311.py
coherent_build-0.35.2.dist-info/licenses/LICENSE
coherent_build-0.35.2.dist-info/WHEEL
coherent_build-0.35.2.dist-info/METADATA
coherent_build-0.35.2.dist-info/RECORD
