Metadata-Version: 2.4
Name: coherent.build
Version: 0.35.2
Summary: A zero-config Python project build backend
Author-email: "Jason R. Coombs" <jaraco@jaraco.com>
Requires-Python: >= 3.9
License-Expression: MIT
Classifier: Development Status :: 4 - Beta
Classifier: Intended Audience :: Developers
Classifier: Programming Language :: Python :: 3
Classifier: Programming Language :: Python :: 3 :: Only
License-File: LICENSE
Requires-Dist: build
Requires-Dist: git-fame
Requires-Dist: importlib_resources; python_version < "3.12"
Requires-Dist: jaraco.compat
Requires-Dist: jaraco.functools
Requires-Dist: more-itertools
Requires-Dist: wheel
Requires-Dist: python-gitlab
Requires-Dist: jaraco.vcs
Requires-Dist: packaging
Requires-Dist: requests
Requires-Dist: setuptools-scm
Requires-Dist: jaraco.context
Requires-Dist: pip-run
Requires-Dist: coherent.deps
Requires-Dist: coherent.licensed
Requires-Dist: importlib_metadata
Requires-Dist: tomlkit
Project-URL: Source, https://github.com/coherent-oss/coherent.build
